rest_framework_multitoken/__init__.py
rest_framework_multitoken/admin.py
rest_framework_multitoken/apps.py
rest_framework_multitoken/authentication.py
rest_framework_multitoken/models.py
rest_framework_multitoken/utils.py
rest_framework_multitoken/views.py
rest_framework_multitoken/management/commands/__init__.py
rest_framework_multitoken/management/commands/multitoken_sync.py
rest_framework_multitoken/migrations/0001_initial.py
rest_framework_multitoken/migrations/__init__.py
djangorestframework_multitoken-0.1.dist-info/LICENSE
djangorestframework_multitoken-0.1.dist-info/METADATA
djangorestframework_multitoken-0.1.dist-info/WHEEL
djangorestframework_multitoken-0.1.dist-info/top_level.txt
djangorestframework_multitoken-0.1.dist-info/RECORD
