Metadata-Version: 2.1
Name: djangorestframework-multitoken
Version: 0.1
Summary: Version of Django REST Framework auth Token allowing multiple Tokens per User.
Home-page: https://gitlab.com/nextlink/djangorestframework-multitoken
Author: NextLink Labs
License: MIT
Platform: UNKNOWN
Classifier: Environment :: Web Environment
Classifier: Framework :: Django
Classifier: Intended Audience :: Developers
Classifier: License :: OSI Approved :: BSD License
Classifier: Operating System :: OS Independent
Classifier: Programming Language :: Python :: 3
Requires-Python: >=3.6
License-File: LICENSE
Requires-Dist: djangorestframework (>=3.12)
